chronos/__init__.py
chronos/api/__init__.py
chronos/cli/__init__.py
chronos/cli/main.py
chronos/cli/commands/__init__.py
chronos/cli/commands/analyze.py
chronos/cli/commands/config.py
chronos/cli/commands/defend.py
chronos/cli/commands/detect.py
chronos/cli/commands/intel.py
chronos/cli/commands/ir.py
chronos/cli/commands/logs.py
chronos/cli/commands/phishing.py
chronos/cli/commands/report.py
chronos/cli/commands/vuln.py
chronos/cli/utils/__init__.py
chronos/cli/utils/config.py
chronos/cli/utils/helpers.py
chronos/cli/utils/logger.py
chronos/core/__init__.py
chronos/core/config.py
chronos/core/database.py
chronos/core/exceptions.py
chronos/core/intel.py
chronos/core/logs.py
chronos/core/phishing.py
chronos/core/playbooks.py
chronos/core/reports.py
chronos/core/scanner.py
chronos/core/schema.py
chronos/core/settings.py
chronos/core/vuln.py
chronos/core/detect/__init__.py
chronos/core/detect/darkweb_monitor.py
chronos/core/detect/hndl_detector.py
chronos/core/detect/models.py
chronos/core/detect/network_monitor.py
chronos/crypto/__init__.py
chronos/integrations/__init__.py
chronos/models/__init__.py
chronos/models/security.py
chronos/models/threat.py
chronos/utils/__init__.py
chronos/utils/logging.py
chronos_security-1.1.5.dist-info/licenses/LICENSE
chronos_security-1.1.5.dist-info/METADATA
chronos_security-1.1.5.dist-info/WHEEL
chronos_security-1.1.5.dist-info/entry_points.txt
chronos_security-1.1.5.dist-info/top_level.txt
chronos_security-1.1.5.dist-info/RECORD
