Metadata-Version: 2.4
Name: chronos-security
Version: 1.1.5
Summary: Unified Security Fusion Platform - Threat Intelligence, Vulnerability Management, IR Playbooks
Home-page: https://github.com/yourusername/CHRONOS
Author: CHRONOS Security Team
Author-email: CHRONOS Security Team <team@chronos-security.io>
License: MIT
Project-URL: Homepage, https://github.com/yourusername/CHRONOS
Project-URL: Documentation, https://chronos-security.io/docs
Project-URL: Repository, https://github.com/yourusername/CHRONOS
Project-URL: Issues, https://github.com/yourusername/CHRONOS/issues
Keywords: security,threat-intelligence,vulnerability-management,cve,epss,phishing,incident-response,cybersecurity,infosec
Classifier: Development Status :: 5 - Production/Stable
Classifier: Intended Audience :: Developers
Classifier: License :: OSI Approved :: MIT License
Classifier: Programming Language :: Python :: 3
Classifier: Programming Language :: Python :: 3.10
Classifier: Programming Language :: Python :: 3.11
Classifier: Programming Language :: Python :: 3.12
Classifier: Topic :: Security
Classifier: Topic :: Security :: Cryptography
Requires-Python: >=3.10
License-File: LICENSE
Requires-Dist: click>=8.1.0
Requires-Dist: typer>=0.9.0
Requires-Dist: rich>=13.0.0
Requires-Dist: pyyaml>=6.0.0
Requires-Dist: python-dotenv>=1.0.0
Requires-Dist: pydantic>=2.0.0
Requires-Dist: pydantic-settings>=2.0.0
Requires-Dist: cryptography>=41.0.0
Requires-Dist: httpx>=0.25.0
Requires-Dist: scikit-learn>=1.3.0
Requires-Dist: numpy>=1.24.0
Requires-Dist: matplotlib>=3.8.0
Requires-Dist: jinja2>=3.1.0
Provides-Extra: dev
Requires-Dist: pytest>=7.4.0; extra == "dev"
Requires-Dist: pytest-asyncio>=0.21.0; extra == "dev"
Requires-Dist: pytest-cov>=4.1.0; extra == "dev"
Requires-Dist: black>=23.0.0; extra == "dev"
Requires-Dist: ruff>=0.1.0; extra == "dev"
Requires-Dist: mypy>=1.5.0; extra == "dev"
Requires-Dist: pre-commit>=3.5.0; extra == "dev"
Provides-Extra: docs
Requires-Dist: mkdocs>=1.5.0; extra == "docs"
Requires-Dist: mkdocs-material>=9.4.0; extra == "docs"
Dynamic: author
Dynamic: home-page
Dynamic: license-file
Dynamic: requires-python
